deepclaw/__init__.py
deepclaw/driver/__init__.py
deepclaw/driver/arms/ArmController.py
deepclaw/driver/arms/UR10eController.py
deepclaw/driver/arms/UR5Controller.py
deepclaw/driver/arms/URConnector.py
deepclaw/driver/arms/__init__.py
deepclaw/modules/HelloDC.py
deepclaw/modules/__init__.py
deepclaw/modules/calibration/EyeOnBase.py
deepclaw/modules/calibration/__init__.py
deepclaw/modules/segmentation/ContourDetector.py
deepclaw/modules/segmentation/__init__.py
deepclaw/utils/Client.py
deepclaw/utils/IO.py
deepclaw/utils/Math.py
deepclaw/utils/Server.py
deepclaw/utils/__init__.py
deepclaw/utils/success_label/DetectForeground.py
deepclaw/utils/success_label/__init__.py
deepclaw/utils/success_label/success_label.py
DeepClaw-1.0.2.dist-info/METADATA
DeepClaw-1.0.2.dist-info/WHEEL
DeepClaw-1.0.2.dist-info/top_level.txt
DeepClaw-1.0.2.dist-info/RECORD
