Metadata-Version: 2.1
Name: DeepClaw
Version: 1.0.2
Summary: a reconfigurable benchmark of robotic hardware and task hierarchy for robot learning
Home-page: https://bionicdl-sustech.github.io/DeepClawBenchmark/_build/html/index.html
Author: BionicDL
Author-email: sirgroup@outlook.com
Maintainer: Haokun W., Fang W., Xiaobo L., Yanglin H.
Maintainer-email: wanghk@mail.sustech.edu.cn
License: MIT License
Platform: all
Classifier: Development Status :: 4 - Beta
Classifier: Intended Audience :: Developers
Classifier: License :: OSI Approved :: MIT License
Classifier: Programming Language :: Python :: 3.7
Classifier: Programming Language :: Python :: 3.8
Classifier: Topic :: Software Development :: Libraries
Requires-Dist: numpy (>=1.18)
